{
  "version": 1.3,
  "people": [
    {
      "person_id": [
        -1
      ],
      "pose_keypoints_2d": [
        418.722,
        726.423,
        0.777311,
        440.515,
        741.592,
        0.901716,
        433.39,
        741.632,
        0.833674,
        389.236,
        792.888,
        0.673743,
        345.289,
        793.232,
        0.614683,
        440.898,
        741.473,
        0.886084,
        382.383,
        778.233,
        0.737811,
        330.932,
        785.783,
        0.664375,
        448.075,
        866.196,
        0.824427,
        440.541,
        866.179,
        0.873763,
        433.547,
        961.639,
        0.934822,
        426.051,
        1027.86,
        0.877139,
        477.209,
        866.15,
        0.812142,
        484.485,
        961.851,
        0.88154,
        491.686,
        1056.94,
        0.859466,
        425.997,
        719.575,
        0.277688,
        425.973,
        712.272,
        0.776691,
        433.457,
        719.619,
        0.0733807,
        440.432,
        719.481,
        0.851435,
        447.933,
        1071.8,
        0.834005,
        470.179,
        1078.91,
        0.820147,
        491.903,
        1064.42,
        0.826928,
        389.485,
        1049.54,
        0.723691,
        389.494,
        1035.05,
        0.725075,
        433.119,
        1035.05,
        0.705267
      ],
      "face_keypoints_2d": [],
      "hand_left_keypoints_2d": [],
      "hand_right_keypoints_2d": [],
      "pose_keypoints_3d": [],
      "face_keypoints_3d": [],
      "hand_left_keypoints_3d": [],
      "hand_right_keypoints_3d": []
    }
  ]
}